zensols/mednlp/resources/app.conf
zensols/mednlp/resources/bioner.yml
zensols/mednlp/resources/ctakes.conf
zensols/mednlp/resources/cui2vec.yml
zensols/mednlp/resources/default.conf
zensols/mednlp/resources/entlink.conf
zensols/mednlp/resources/filter-medical.conf
zensols/mednlp/resources/install-v1.conf
zensols/mednlp/resources/install-v2.conf
zensols/mednlp/resources/install.conf
zensols/mednlp/resources/lang.conf
zensols/mednlp/resources/obj.conf
zensols/mednlp/resources/pyrush.conf
zensols/mednlp/resources/transformer-sent.conf
zensols/mednlp/resources/uts.conf
zensols/mednlp/resources/metamap/umls-groups.txt
zensols/mednlp/resources/metamap/umls-tuis.txt
zensols/mednlp/__init__.py
zensols/mednlp/app.py
zensols/mednlp/cli.py
zensols/mednlp/ctakes.py
zensols/mednlp/cui2vec.py
zensols/mednlp/domain.py
zensols/mednlp/entlink.py
zensols/mednlp/lib.py
zensols/mednlp/parser.py
zensols/mednlp/resource.py
zensols/mednlp/tok.py
zensols/mednlp/uts.py
zensols_mednlp-1.9.2.dist-info/METADATA
zensols_mednlp-1.9.2.dist-info/WHEEL
zensols_mednlp-1.9.2.dist-info/entry_points.txt
zensols_mednlp-1.9.2.dist-info/licenses/LICENSE.md
zensols_mednlp-1.9.2.dist-info/RECORD
