Metadata-Version: 2.3
Name: zensols_mednlp
Version: 1.9.2
Summary: A natural language medical domain parsing library.
Project-URL: Homepage, https://github.com/plandes/mednlp
Project-URL: Documentation, https://plandes.github.io/mednlp
Project-URL: Repository, https://github.com/plandes/mednlp.git
Project-URL: Issues, https://github.com/plandes/mednlp/issues
Project-URL: Changelog, https://github.com/plandes/mednlp/blob/master/CHANGELOG.md
Author-email: Paul Landes <landes@mailc.net>
License: MIT
Keywords: clinical,entity linking,natural language processing
Requires-Python: <3.13,>=3.11
Requires-Dist: ctakes-parser~=0.1.0
Requires-Dist: lxml~=4.9.3
Requires-Dist: medcat~=1.16.0
Requires-Dist: numpy~=1.26.4
Requires-Dist: pandas~=2.3.0
Requires-Dist: scikit-learn~=1.3.2
Requires-Dist: scipy~=1.13.1
Requires-Dist: scispacy~=0.5.4
Requires-Dist: zensols-install~=1.2.0
Requires-Dist: zensols-nlp~=1.12.7
